arvan_client/__init__.py
arvan_client/arvan/__init__.py
arvan_client/arvan/api.py
arvan_client/arvan/types.py
arvan_client/dns/__init__.py
arvan_client/dns/dns.py
arvan_client/dns/domain.py
arvan_client/vod/__init__.py
arvan_client/vod/channel.py
arvan_client/vod/video.py
arvan_client/vod/vod.py
arvan_client-0.0.6.dist-info/LICENSE
arvan_client-0.0.6.dist-info/METADATA
arvan_client-0.0.6.dist-info/WHEEL
arvan_client-0.0.6.dist-info/top_level.txt
arvan_client-0.0.6.dist-info/RECORD
