Metadata-Version: 2.1
Name: arvan-client
Version: 0.0.6
Summary: A Python SDK for ArvanCloud API
Home-page: https://github.com/sajadrahimi/arvan-client
Author: Sajad Rahimi
Author-email: rahimisajad@outlook.com
License: UNKNOWN
Project-URL: Bug Tracker, https://github.com/sajadrahimi/arvan-client/issues
Platform: UNKNOWN
Classifier: Programming Language :: Python :: 3
Classifier: License :: OSI Approved :: MIT License
Classifier: Operating System :: OS Independent
Requires-Python: >=3.6
